[
    {
        "title": "Software Engineer, University Graduate, 2025",
        "company": "Google",
        "location": "Gurgaon, Haryana, India",
        "skills required": [
            "linux",
            "unix",
            "machine learning",
            "natural language processing",
            "c++",
            "java",
            "python",
            "ui design",
            "macos",
            "scalability",
            "tcp/ip",
            "leadership",
            "android",
            "windows"
        ],
        "seniority level": "Entry level",
        "employment type": "Full-time",
        "job function": "Information Technology and Engineering",
        "industries": "Information Services and Technology, Information and Internet",
        "list_date": "2 weeks ago"
    },
    {
        "title": "Software Engineer - Backend",
        "company": "HDFC Bank",
        "location": "Gurugram, Haryana, India",
        "skills required": [
            "java",
            "kubernetes",
            "performance tuning",
            "microservices",
            "spring boot"
        ],
        "seniority level": "Mid-Senior level",
        "employment type": "Full-time",
        "job function": "Project Management and Product Management",
        "industries": "Banking and Software Development",
        "list_date": "1 week ago"
    },
    {
        "title": "Software Engineer II, Full Stack, Google Cloud",
        "company": "Google",
        "location": "Gurugram, Haryana, India",
        "skills required": [
            "natural language processing",
            "go",
            "c++",
            "javascript",
            "python",
            "java",
            "ui design",
            "typescript",
            "css",
            "html",
            "leadership"
        ],
        "seniority level": "Not Applicable",
        "employment type": "Full-time",
        "job function": "Information Technology and Engineering",
        "industries": "Information Services and Technology, Information and Internet",
        "list_date": "6 days ago"
    },
    {
        "title": "Software Engineer- Backend",
        "company": "Trackier",
        "location": "Noida, Uttar Pradesh, India",
        "skills required": [
            "cassandra",
            "integration testing",
            "javascript",
            "jenkins",
            "css",
            "html",
            "angular",
            "mongodb",
            "node.js",
            "php"
        ],
        "seniority level": "Associate",
        "employment type": "Full-time",
        "job function": "Engineering",
        "industries": "Non-profit Organizations and Primary and Secondary Education",
        "list_date": "4 months ago"
    },
    {
        "title": "Full Stack Developer- Leading Group",
        "company": "Headsup Corporation",
        "location": "Gurugram, Haryana, India",
        "skills required": [
            "microservices architecture",
            "mysql",
            "javascript",
            "aws",
            "redis",
            "typescript",
            "gcp",
            "mongodb",
            "microservices",
            "node.js",
            "svn",
            "git"
        ],
        "seniority level": "Associate",
        "employment type": "Full-time",
        "job function": "Engineering and Information Technology",
        "industries": "Human Resources Services",
        "list_date": "4 months ago"
    },
    {
        "title": "Full Stack Developer",
        "company": "SaaS Labs",
        "location": "Delhi, India",
        "skills required": [
            "mysql",
            "css",
            "html",
            "php",
            "jquery"
        ],
        "seniority level": "Mid-Senior level",
        "employment type": "Full-time",
        "job function": "Engineering and Information Technology",
        "industries": "Software Development",
        "list_date": "1 year ago"
    },
    {
        "title": "Software Developer - Backend",
        "company": "Addwiser",
        "location": "Noida, Uttar Pradesh, India",
        "skills required": [
            "javascript",
            "problem-solving",
            "communication",
            "sql",
            "angular",
            "microservices",
            "c#",
            "aws"
        ],
        "seniority level": "Entry level",
        "employment type": "Full-time",
        "job function": "Engineering and Information Technology",
        "industries": "Software Development and IT Services and IT Consulting",
        "list_date": "5 months ago"
    },
    {
        "title": "Full Stack Developer",
        "company": "Flyzy",
        "location": "Gurgaon, Haryana, India",
        "skills required": [
            "react.js",
            "problem-solving",
            "javascript",
            "next.js",
            "css",
            "collaboration",
            "node.js"
        ],
        "seniority level": "Entry level",
        "employment type": "Full-time",
        "job function": "Engineering and Information Technology",
        "industries": "IT Services and IT Consulting",
        "list_date": "10 months ago"
    },
    {
        "title": "Full Stack Developer (React/Node)",
        "company": "Sinch",
        "location": "Noida, Uttar Pradesh, India",
        "skills required": [
            "mysql",
            "javascript",
            "communication",
            "graphql",
            "unit testing",
            "agile methodologies",
            "teamwork",
            "node.js"
        ],
        "seniority level": "Not Applicable",
        "employment type": "Full-time",
        "job function": "Engineering and Information Technology",
        "industries": "Telecommunications",
        "list_date": "1 week ago"
    },
    {
        "title": "Full stack Developer",
        "company": "Teamwork Arts Pvt Ltd",
        "location": "Delhi, India",
        "skills required": [
            "mysql",
            "javascript",
            "problem-solving",
            "bootstrap",
            "user interface",
            "ui design",
            "communication",
            "css",
            "html",
            "sql",
            "angular",
            "wordpress",
            "user experience",
            "node.js",
            "php",
            "jquery"
        ],
        "seniority level": "Mid-Senior level",
        "employment type": "Full-time",
        "job function": "Engineering and Information Technology",
        "industries": "Entertainment",
        "list_date": "7 months ago"
    },
    {
        "title": "Full Stack Developer",
        "company": "Skye Air Mobility",
        "location": "Gurgaon, Haryana, India",
        "skills required": [
            "docker",
            "mysql",
            "ci/cd",
            "jenkins",
            "python",
            "java",
            "gitlab",
            "kubernetes",
            "sql",
            "unit testing",
            "angular",
            "mongodb",
            "microservices",
            "aws",
            "scalability"
        ],
        "seniority level": "Not Applicable",
        "employment type": "Full-time",
        "job function": "Engineering and Information Technology",
        "industries": "Aviation and Aerospace Component Manufacturing",
        "list_date": "1 year ago"
    },
    {
        "title": "Software Engineer",
        "company": "PhoneCurry.Com",
        "location": "Delhi, India",
        "skills required": [
            "mysql",
            "bootstrap",
            "css",
            "html",
            "jquery",
            "php"
        ],
        "seniority level": "Entry level",
        "employment type": "Full-time",
        "job function": "Engineering and Information Technology",
        "industries": "Computers and Electronics Manufacturing",
        "list_date": "1 year ago"
    },
    {
        "title": "Full Stack Developer",
        "company": "Gigmo Solutions",
        "location": "Gurugram, Haryana, India",
        "skills required": [
            "ci/cd",
            "django",
            "javascript",
            "docker",
            "python",
            "flask",
            "kubernetes",
            "sql",
            "user experience",
            "aws",
            "git",
            "windows"
        ],
        "seniority level": "Mid-Senior level",
        "employment type": "Full-time",
        "job function": "Information Technology",
        "industries": "Non-profit Organizations and Primary and Secondary Education",
        "list_date": "2 weeks ago"
    },
    {
        "title": "Full Stack Developer Intern",
        "company": "Cypherock",
        "location": "Ghaziabad, Uttar Pradesh, India",
        "skills required": [
            "blockchain",
            "amazon web services",
            "typescript",
            "aws",
            "github"
        ],
        "seniority level": "Entry level",
        "employment type": "Full-time",
        "job function": "Engineering and Information Technology",
        "industries": "Computers and Electronics Manufacturing",
        "list_date": "1 year ago"
    },
    {
        "title": "Full Stack Developer",
        "company": "CogniTensor",
        "location": "Faridabad, Haryana, India",
        "skills required": [
            "ci/cd",
            "amazon web services",
            "python",
            "html",
            "teamwork",
            "bitbucket",
            "git",
            "docker",
            "react.js",
            "react native",
            "agile methodologies",
            "aws",
            "communication",
            "css",
            "node.js",
            "windows",
            "graphql",
            "jira",
            "android"
        ],
        "seniority level": "Mid-Senior level",
        "employment type": "Full-time",
        "job function": "Engineering and Information Technology",
        "industries": "IT Services and IT Consulting",
        "list_date": "1 year ago"
    },
    {
        "title": "Full Stack Developer- Intern",
        "company": "EYE MANTRA",
        "location": "Delhi, Delhi, India",
        "skills required": [
            "mysql",
            "git",
            "javascript",
            "bootstrap",
            "communication",
            "css",
            "html",
            "express.js",
            "jquery",
            "node.js",
            "php"
        ],
        "seniority level": "Internship",
        "employment type": "Internship",
        "job function": "Engineering and Information Technology",
        "industries": "Staffing and Recruiting",
        "list_date": "3 months ago"
    },
    {
        "title": "Full Stack Developer",
        "company": "Jain Software",
        "location": "New Rajendra Nagar, Delhi, India",
        "skills required": [
            "mysql",
            "javascript",
            "laravel",
            "css",
            "html",
            "wordpress",
            "magento",
            "php"
        ],
        "seniority level": "Mid-Senior level",
        "employment type": "Full-time",
        "job function": "Engineering and Information Technology",
        "industries": "IT Services and IT Consulting",
        "list_date": "7 months ago"
    },
    {
        "title": "Backend Developer",
        "company": "Tamcherry",
        "location": "Gurgaon, Haryana, India",
        "skills required": [
            "ruby on rails",
            "python",
            "mongodb",
            "ruby",
            "spring boot",
            "aws",
            "scalability",
            "microservices architecture",
            "cassandra",
            "postgresql",
            "django",
            "java",
            "communication",
            "collaboration",
            "microservices",
            "node.js",
            "blockchain",
            "mysql",
            "problem-solving"
        ],
        "seniority level": "Mid-Senior level",
        "employment type": "Full-time",
        "job function": "Engineering and Information Technology",
        "industries": "Information Technology & Services",
        "list_date": "4 months ago"
    },
    {
        "title": "Full Stack Developer",
        "company": "Airveda",
        "location": "Gurugram, Haryana, India",
        "skills required": [
            "mysql",
            "django",
            "javascript",
            "problem-solving",
            "postgresql",
            "python",
            "flask",
            "communication",
            "css",
            "html",
            "sql",
            "angular",
            "collaboration",
            "vue.js",
            "iot",
            "monitoring",
            "git"
        ],
        "seniority level": "Associate",
        "employment type": "Full-time",
        "job function": "Engineering and Information Technology",
        "industries": "Technology, Information and Internet",
        "list_date": "2 months ago"
    },
    {
        "title": "Full Stack Developer",
        "company": "CogniTensor",
        "location": "Noida, Uttar Pradesh, India",
        "skills required": [
            "ci/cd",
            "docker",
            "python",
            "communication",
            "css",
            "html",
            "react native",
            "graphql",
            "agile methodologies",
            "teamwork",
            "mongodb",
            "aws",
            "bitbucket",
            "git",
            "android",
            "jira"
        ],
        "seniority level": "Mid-Senior level",
        "employment type": "Full-time",
        "job function": "Engineering and Information Technology",
        "industries": "IT Services and IT Consulting",
        "list_date": "1 year ago"
    },
    {
        "title": "JavaScript Developer",
        "company": "INVIDEV",
        "location": "Ghaziabad, Uttar Pradesh, India",
        "skills required": [
            "ionic",
            "mysql",
            "javascript",
            "node.js",
            "css",
            "html",
            "mongodb",
            "firebase",
            "php",
            "jquery"
        ],
        "seniority level": "Entry level",
        "employment type": "Full-time",
        "job function": "Engineering and Information Technology",
        "industries": "Staffing and Recruiting",
        "list_date": "1 week ago"
    },
    {
        "title": "Full Stack JavaScript Developer - React.js/Redux/Node.js",
        "company": "Camp K12",
        "location": "Delhi, India",
        "skills required": [
            "webrtc",
            "react.js",
            "javascript",
            "node.js",
            "figma",
            "redis",
            "sketch",
            "communication",
            "mongodb",
            "firebase"
        ],
        "seniority level": "Entry level",
        "employment type": "Full-time",
        "job function": "Engineering and Information Technology",
        "industries": "E-Learning Providers",
        "list_date": "1 year ago"
    },
    {
        "title": "Software Engineer II",
        "company": "Microsoft",
        "location": "Delhi, India",
        "skills required": [
            "linux",
            "go",
            "mysql",
            "docker",
            "ci/cd",
            "java",
            "python",
            "kubernetes",
            "time management",
            "collaboration",
            "c#",
            "scalability",
            "windows"
        ],
        "seniority level": "Not Applicable",
        "employment type": "Full-time",
        "job function": "Engineering and Information Technology",
        "industries": "Software Development",
        "list_date": "6 days ago"
    },
    {
        "title": "Full Stack Developer",
        "company": "Umanist Staffing",
        "location": "Gurgaon, Haryana, India",
        "skills required": [
            "ci/cd",
            "javascript",
            "problem-solving",
            "communication",
            "sql",
            "html",
            "css",
            "user experience",
            "teamwork",
            "node.js",
            "aws",
            "scalability"
        ],
        "seniority level": "Associate",
        "employment type": "Full-time",
        "job function": "Engineering and Information Technology",
        "industries": "Business Consulting and Services",
        "list_date": "5 days ago"
    },
    {
        "title": "Junior Full Stack developer",
        "company": "techugo",
        "location": "Noida, Uttar Pradesh, India",
        "skills required": [
            "communication"
        ],
        "seniority level": "Associate",
        "employment type": "Full-time",
        "job function": "Engineering and Information Technology",
        "industries": "IT Services and IT Consulting",
        "list_date": "2 days ago"
    },
    {
        "title": "Full Stack Engineer",
        "company": "BT Group",
        "location": "Gurugram, Haryana, India",
        "skills required": [
            "problem-solving",
            "typescript",
            "communication",
            "monitoring",
            "agile methodologies",
            "aws",
            "leadership",
            "project management",
            "jira"
        ],
        "seniority level": "Mid-Senior level",
        "employment type": "Full-time",
        "job function": "Engineering and Information Technology",
        "industries": "Telecommunications",
        "list_date": "2 weeks ago"
    },
    {
        "title": "Full-stack Developer",
        "company": "Addwiser",
        "location": "Delhi Cantonment, Delhi, India",
        "skills required": [
            "microservices architecture",
            "dynamodb",
            "docker",
            "react.js",
            "javascript",
            "automated testing",
            "amazon web services",
            "typescript",
            "kubernetes",
            "graphql",
            "react native",
            "microservices",
            "node.js",
            "aws",
            "git"
        ],
        "seniority level": "Entry level",
        "employment type": "Full-time",
        "job function": "Engineering and Information Technology",
        "industries": "Software Development",
        "list_date": "1 month ago"
    },
    {
        "title": "Full Stack Developer - Python &amp; React.js",
        "company": "Gigmo Solutions",
        "location": "Gurugram, Haryana, India",
        "skills required": [
            "ci/cd",
            "django",
            "javascript",
            "docker",
            "python",
            "flask",
            "kubernetes",
            "sql",
            "user experience",
            "aws",
            "git",
            "windows"
        ],
        "seniority level": "Entry level",
        "employment type": "Full-time",
        "job function": "Information Technology",
        "industries": "Technology, Information and Internet, Software Development, and Technology, Information and Media",
        "list_date": "1 week ago"
    },
    {
        "title": "Full Stack Developer",
        "company": "VECROS",
        "location": "Delhi, Delhi, India",
        "skills required": [
            "docker",
            "django",
            "javascript",
            "python",
            "aws"
        ],
        "seniority level": "Entry level",
        "employment type": "Internship",
        "job function": "Engineering and Information Technology",
        "industries": "Automation Machinery Manufacturing",
        "list_date": "1 year ago"
    },
    {
        "title": "Frontend Developer",
        "company": "Housing.com",
        "location": "Gurugram, Haryana, India",
        "skills required": [
            "ruby",
            "microservices architecture",
            "docker",
            "mysql",
            "javascript",
            "java",
            "redis",
            "kubernetes",
            "graphql",
            "nginx",
            "html",
            "css",
            "elasticsearch",
            "microservices",
            "aws",
            "git",
            "android"
        ],
        "seniority level": "Associate",
        "employment type": "Full-time",
        "job function": "Design and Information Technology",
        "industries": "Real Estate and Internet Marketplace Platforms",
        "list_date": "10 hours ago"
    },
    {
        "title": "Full Stack Developer",
        "company": "CodersBrain",
        "location": "Noida, Uttar Pradesh, India",
        "skills required": [
            "angular",
            "php"
        ],
        "seniority level": "Mid-Senior level",
        "employment type": "Full-time",
        "job function": "Engineering and Information Technology",
        "industries": "IT Services and IT Consulting",
        "list_date": "1 year ago"
    },
    {
        "title": "Full Stack Developer",
        "company": "Orangewood",
        "location": "Noida, Uttar Pradesh, India",
        "skills required": [
            "react.js",
            "javascript",
            "communication",
            "css",
            "html",
            "restful apis",
            "vue.js",
            "collaboration",
            "node.js"
        ],
        "seniority level": "Internship",
        "employment type": "Part-time",
        "job function": "Engineering",
        "industries": "Manufacturing",
        "list_date": "5 months ago"
    },
    {
        "title": "Full Stack React JS Developer",
        "company": "Iksha Labs",
        "location": "Noida, Uttar Pradesh, India",
        "skills required": [
            "machine learning",
            "react.js",
            "virtual reality",
            "augmented reality",
            "bootstrap",
            "css",
            "html",
            "node.js"
        ],
        "seniority level": "Mid-Senior level",
        "employment type": "Full-time",
        "job function": "Engineering and Information Technology",
        "industries": "Software Development",
        "list_date": "1 year ago"
    },
    {
        "title": "Full Stack (Mean/Mern) Developer",
        "company": "The Staffers (Generation Next)",
        "location": "Gurgaon, Haryana, India",
        "skills required": [
            "ruby",
            "sass",
            "mysql",
            "postgresql",
            "javascript",
            "python",
            "bootstrap",
            "java",
            "css",
            "html",
            "express.js",
            "angular",
            "mongodb",
            "node.js",
            "php",
            "jquery"
        ],
        "seniority level": "Associate",
        "employment type": "Full-time",
        "job function": "Other",
        "industries": "Staffing and Recruiting",
        "list_date": "2 days ago"
    },
    {
        "title": "Software Engineer II",
        "company": "Microsoft",
        "location": "Delhi, India",
        "skills required": [
            "linux",
            "mysql",
            "docker",
            "ci/cd",
            "java",
            "python",
            "scalability",
            "time management",
            "collaboration",
            "spring boot",
            "git"
        ],
        "seniority level": "Not Applicable",
        "employment type": "Full-time",
        "job function": "Engineering and Information Technology",
        "industries": "Software Development",
        "list_date": "6 days ago"
    },
    {
        "title": "Full Stack Developer",
        "company": "Sambhav Pay",
        "location": "Gurgaon, Haryana, India",
        "skills required": [
            "mysql",
            "postgresql",
            "javascript",
            "problem-solving",
            "embedded systems",
            "java",
            "python",
            "communication",
            "css",
            "html",
            "angular",
            "mongodb",
            "api development",
            "teamwork",
            "node.js"
        ],
        "seniority level": "Mid-Senior level",
        "employment type": "Full-time",
        "job function": "Engineering and Information Technology",
        "industries": "Banking, Investment Banking, and Information Technology & Services",
        "list_date": "2 days ago"
    },
    {
        "title": "Full Stack Developer",
        "company": "Sambhav Pay",
        "location": "Gurgaon, Haryana, India",
        "skills required": [
            "mysql",
            "postgresql",
            "javascript",
            "problem-solving",
            "embedded systems",
            "java",
            "python",
            "communication",
            "css",
            "html",
            "angular",
            "mongodb",
            "api development",
            "teamwork",
            "node.js"
        ],
        "seniority level": "Mid-Senior level",
        "employment type": "Full-time",
        "job function": "Engineering and Information Technology",
        "industries": "Financial Services",
        "list_date": "2 days ago"
    },
    {
        "title": "Full Stack Developer",
        "company": "Sambhav Pay",
        "location": "Gurgaon, Haryana, India",
        "skills required": [
            "mysql",
            "postgresql",
            "javascript",
            "problem-solving",
            "embedded systems",
            "java",
            "python",
            "communication",
            "css",
            "html",
            "angular",
            "mongodb",
            "api development",
            "teamwork",
            "node.js"
        ],
        "seniority level": "Mid-Senior level",
        "employment type": "Full-time",
        "job function": "Engineering and Information Technology",
        "industries": "Banking, Investment Banking, and Information Technology & Services",
        "list_date": "2 days ago"
    },
    {
        "title": "Full Stack Developer - MySQL | Node.js |React.js",
        "company": "StoryXpress",
        "location": "Gurugram, Haryana, India",
        "skills required": [
            "mysql",
            "react.js",
            "javascript",
            "postgresql",
            "redis",
            "express.js",
            "html",
            "css",
            "node.js",
            "git"
        ],
        "seniority level": "Mid-Senior level",
        "employment type": "Full-time",
        "job function": "Engineering and Information Technology",
        "industries": "Software Development",
        "list_date": "1 year ago"
    },
    {
        "title": "Full Stack Developer",
        "company": "A1Apps",
        "location": "Gurugram, Haryana, India",
        "skills required": [
            "docker",
            "ci/cd",
            "javascript",
            "react.js",
            "scrum",
            "java",
            "communication",
            "css",
            "html",
            "node.js",
            "aws",
            "jquery"
        ],
        "seniority level": "Mid-Senior level",
        "employment type": "Full-time",
        "job function": "Engineering and Information Technology",
        "industries": "Mobile Computing Software Products",
        "list_date": "1 week ago"
    },
    {
        "title": "Full Stack Developer",
        "company": "Geetanjali Homestate Pvt Ltd",
        "location": "Gurgaon, Haryana, India",
        "skills required": [
            "ruby",
            "mysql",
            "javascript",
            "problem-solving",
            "python",
            "java",
            "communication",
            "css",
            "html",
            "angular",
            "mongodb",
            "php",
            "project management"
        ],
        "seniority level": "Executive",
        "employment type": "Full-time",
        "job function": "Engineering and Information Technology",
        "industries": "Real Estate",
        "list_date": "2 days ago"
    },
    {
        "title": "Senior Software Engineer, Google Cloud",
        "company": "Google",
        "location": "Gurgaon, Haryana, India",
        "skills required": [
            "natural language processing",
            "ui design",
            "leadership"
        ],
        "seniority level": "Mid-Senior level",
        "employment type": "Full-time",
        "job function": "Information Technology and Engineering",
        "industries": "Information Services and Technology, Information and Internet",
        "list_date": "2 weeks ago"
    },
    {
        "title": "Full Stack Developer",
        "company": "Axtria - Ingenious Insights",
        "location": "Noida, Uttar Pradesh, India",
        "skills required": [
            "django",
            "javascript",
            "python",
            "flask",
            "typescript",
            "sql",
            "html",
            "aws"
        ],
        "seniority level": "Associate",
        "employment type": "Full-time",
        "job function": "Information Technology",
        "industries": "IT System Custom Software Development, IT System Design Services, and IT System Data Services",
        "list_date": "1 week ago"
    },
    {
        "title": "Backend Developer | Noida",
        "company": "Qrata",
        "location": "Delhi, India",
        "skills required": [
            "go",
            "cassandra",
            "postgresql",
            "javascript",
            "python",
            "graphql",
            "css",
            "html",
            "sql",
            "elasticsearch",
            "mongodb",
            "node.js"
        ],
        "seniority level": "Mid-Senior level",
        "employment type": "Full-time",
        "job function": "Engineering and Information Technology",
        "industries": "Human Resources",
        "list_date": "1 year ago"
    },
    {
        "title": "Manager, Software Engineer (Full Stack - ReactJS, NodeJS, SQL) (copy)",
        "company": "Nielsen",
        "location": "Gurgaon, Haryana, India",
        "skills required": [
            "linux",
            "unix",
            "shell scripting",
            "postgresql",
            "mysql",
            "python",
            "java",
            "communication",
            "sql",
            "angular",
            "terraform",
            "aws",
            "leadership"
        ],
        "seniority level": "Not Applicable",
        "employment type": "Full-time",
        "job function": "Engineering and Information Technology",
        "industries": "Market Research and Business Consulting and Services",
        "list_date": "3 months ago"
    },
    {
        "title": "Full Stack developer",
        "company": "BlackLight Gaming",
        "location": "Faridabad, Haryana, India",
        "skills required": [
            "mysql",
            "problem-solving",
            "mongodb",
            "javascript"
        ],
        "seniority level": "Mid-Senior level",
        "employment type": "Full-time",
        "job function": "Engineering and Information Technology",
        "industries": "Computer Games",
        "list_date": "9 months ago"
    },
    {
        "title": "Full stack Developer",
        "company": "TrueBlue Inc.",
        "location": "Gurugram, Haryana, India",
        "skills required": [
            "docker",
            "jenkins",
            "scrum",
            "communication",
            "sql",
            "c#",
            "aws"
        ],
        "seniority level": "Mid-Senior level",
        "employment type": "Full-time",
        "job function": "Information Technology",
        "industries": "Software Development",
        "list_date": "1 week ago"
    },
    {
        "title": "MERN Developer(Full Stack Developer)",
        "company": "Jellyfish Technologies",
        "location": "Noida, Uttar Pradesh, India",
        "skills required": [
            "mysql",
            "postgresql",
            "javascript",
            "amazon web services",
            "react.js",
            "typescript",
            "communication",
            "mongodb",
            "node.js",
            "aws",
            "github",
            "git"
        ],
        "seniority level": "Associate",
        "employment type": "Full-time",
        "job function": "Engineering and Information Technology",
        "industries": "IT Services and IT Consulting",
        "list_date": "1 week ago"
    },
    {
        "title": "Full Stack Developer",
        "company": "YO HR Consultancy",
        "location": "Greater Delhi Area",
        "skills required": [
            "figma",
            "mongodb"
        ],
        "seniority level": "Mid-Senior level",
        "employment type": "Full-time",
        "job function": "Engineering and Information Technology",
        "industries": "Business Consulting and Services",
        "list_date": "1 month ago"
    },
    {
        "title": "Full Stack Developer",
        "company": "EYE MANTRA",
        "location": "Delhi, Delhi, India",
        "skills required": [
            "mysql",
            "git",
            "javascript",
            "bootstrap",
            "communication",
            "css",
            "html",
            "express.js",
            "jquery",
            "node.js",
            "php"
        ],
        "seniority level": "Mid-Senior level",
        "employment type": "Full-time",
        "job function": "Engineering and Information Technology",
        "industries": "Staffing and Recruiting",
        "list_date": "3 months ago"
    },
    {
        "title": "Full stack Developer",
        "company": "LEAF Wearables",
        "location": "Delhi, India",
        "skills required": [
            "postgresql",
            "amazon web services",
            "scrum",
            "gitlab",
            "css",
            "html",
            "angular",
            "mongodb",
            "node.js",
            "aws",
            "github",
            "bitbucket"
        ],
        "seniority level": "Entry level",
        "employment type": "Full-time",
        "job function": "Engineering and Information Technology",
        "industries": "Public Safety",
        "list_date": "1 year ago"
    },
    {
        "title": "Software Engineer II",
        "company": "Microsoft",
        "location": "Delhi, India",
        "skills required": [
            "ci/cd",
            "git",
            "javascript",
            "node.js",
            "sql",
            "leadership",
            "microsoft azure",
            "teamwork",
            "c#",
            "asp.net"
        ],
        "seniority level": "Not Applicable",
        "employment type": "Full-time",
        "job function": "Engineering and Information Technology",
        "industries": "Software Development",
        "list_date": "6 days ago"
    },
    {
        "title": "Full Stack Developer",
        "company": "Nirmal Vision",
        "location": "Noida, Uttar Pradesh, India",
        "skills required": [
            "javascript",
            "python",
            "flask",
            "redis",
            "nginx",
            "html",
            "mongodb",
            "leadership",
            "docker",
            "react.js",
            "aws",
            "django",
            "bootstrap",
            "css",
            "microservices",
            "mysql",
            "sql",
            "terraform",
            "github"
        ],
        "seniority level": "Mid-Senior level",
        "employment type": "Full-time",
        "job function": "Engineering and Information Technology",
        "industries": "Staffing and Recruiting",
        "list_date": "11 months ago"
    },
    {
        "title": "Full Stack Developer",
        "company": "Blue9 Technologies",
        "location": "Gurugram, Haryana, India",
        "skills required": [
            "mysql",
            "javascript",
            "node.js",
            "ux design",
            "java",
            "python",
            "laravel",
            "communication",
            "css",
            "angular",
            "vue.js",
            "agile methodologies",
            "mongodb",
            "teamwork",
            "c#",
            "php",
            "restful apis",
            "jquery"
        ],
        "seniority level": "Mid-Senior level",
        "employment type": "Full-time",
        "job function": "Engineering and Information Technology",
        "industries": "IT Services and IT Consulting",
        "list_date": "1 year ago"
    },
    {
        "title": "Full Stack Developer",
        "company": "InnerChef",
        "location": "Delhi, India",
        "skills required": [
            "php",
            "javascript"
        ],
        "seniority level": "Entry level",
        "employment type": "Full-time",
        "job function": "Engineering and Information Technology",
        "industries": "Food & Beverages",
        "list_date": "1 year ago"
    },
    {
        "title": "Full Stack Developer - Node.js/React.js",
        "company": "Beebom",
        "location": "Noida, Uttar Pradesh, India",
        "skills required": [
            "mysql",
            "postgresql",
            "javascript",
            "react.js",
            "next.js",
            "java",
            "python",
            "git",
            "css",
            "html",
            "express.js",
            "restful apis",
            "mongodb",
            "node.js",
            "aws",
            "jquery"
        ],
        "seniority level": "Mid-Senior level",
        "employment type": "Full-time",
        "job function": "Information Technology",
        "industries": "Technology, Information and Internet, Software Development, and Technology, Information and Media",
        "list_date": "2 months ago"
    },
    {
        "title": "Web Developer (Full Stack)",
        "company": "Maison Infratech Pvt. Ltd.",
        "location": "Gurugram, Haryana, India",
        "skills required": [
            "problem-solving",
            "html",
            "angular",
            "vue.js",
            "restful apis",
            "node.js",
            "scalability"
        ],
        "seniority level": "Associate",
        "employment type": "Full-time",
        "job function": "Engineering and Information Technology",
        "industries": "Real Estate",
        "list_date": "2 weeks ago"
    },
    {
        "title": "Full Stack Developer",
        "company": "Digi Digital Placement",
        "location": "Noida, Uttar Pradesh, India",
        "skills required": [
            "ci/cd",
            "docker",
            "java",
            "kubernetes",
            "sql",
            "gcp",
            "angular",
            "microservices",
            "spring boot",
            "aws"
        ],
        "seniority level": "Associate",
        "employment type": "Full-time",
        "job function": "Engineering and Information Technology",
        "industries": "IT Services and IT Consulting",
        "list_date": "1 year ago"
    },
    {
        "title": "Career Full Stack Developer",
        "company": "Red Apple Technologies Pvt. Ltd.",
        "location": "Delhi, Delhi, India",
        "skills required": [
            "ci/cd",
            "mysql",
            "javascript",
            "cassandra",
            "ux design",
            "git",
            "communication",
            "css",
            "angular",
            "mongodb",
            "teamwork",
            "agile methodologies",
            "node.js",
            "jquery"
        ],
        "seniority level": "Mid-Senior level",
        "employment type": "Full-time",
        "job function": "Engineering and Information Technology",
        "industries": "Staffing and Recruiting",
        "list_date": "3 months ago"
    },
    {
        "title": "Backend/ Full Stack Developer",
        "company": "FabHotels",
        "location": "Gurgaon, Haryana, India",
        "skills required": [
            "mysql",
            "aws",
            "java",
            "redis",
            "angular",
            "mongodb",
            "monitoring"
        ],
        "seniority level": "Entry level",
        "employment type": "Full-time",
        "job function": "Engineering and Information Technology",
        "industries": "Staffing and Recruiting",
        "list_date": "3 weeks ago"
    }
]